mini_memgraph/__init__.py
mini_memgraph/db.py
mini_memgraph/memgraph.py
mini_memgraph/utility.py
mini_memgraph-0.1.2.dist-info/METADATA
mini_memgraph-0.1.2.dist-info/WHEEL
mini_memgraph-0.1.2.dist-info/RECORD
